README.txt
setup.cfg
setup.py
bit/__init__.py
bit.recipe.android_ndk.egg-info/PKG-INFO
bit.recipe.android_ndk.egg-info/SOURCES.txt
bit.recipe.android_ndk.egg-info/dependency_links.txt
bit.recipe.android_ndk.egg-info/entry_points.txt
bit.recipe.android_ndk.egg-info/namespace_packages.txt
bit.recipe.android_ndk.egg-info/not-zip-safe
bit.recipe.android_ndk.egg-info/requires.txt
bit.recipe.android_ndk.egg-info/top_level.txt
bit/recipe/__init__.py
bit/recipe/android_ndk/__init__.py
bit/recipe/android_ndk/install_android_ndk