Metadata-Version: 1.0
Name: bit.recipe.android-ndk
Version: 0.0.2
Summary: bit foundation android_ndk zc.buildout recipe
Home-page: http://www.python.org/pypi/bit.recipe.android_ndk
Author: Ryan Northey
Author-email: ryan@3ca.org.uk
License: GPL
Keywords: buildout
Platform: UNKNOWN
